bfly.py
bfly-0.1.0.dist-info/METADATA
bfly-0.1.0.dist-info/WHEEL
bfly-0.1.0.dist-info/entry_points.txt
bfly-0.1.0.dist-info/top_level.txt
bfly-0.1.0.dist-info/RECORD
