Metadata-Version: 2.4
Name: bfly
Version: 0.1.0
Summary: Basic Bluesky CLI Tool
License-Expression: GPL-3.0-or-later
Project-URL: Repository, https://github.com/maciakl/bmpv
Project-URL: Issues, https://github.com/maciakl/bmpv/issues
Keywords: bluesky,cli,tool
Requires-Python: >=3.11
Requires-Dist: atproto>=0.0.65
Requires-Dist: termcolor>=3.3.0
